{"is_source_file": false, "format": "", "description": "", "external_files": [], "external_methods": [], "published": [], "classes": [], "methods": [], "calls": [], "search-terms": [], "state": 2, "file_id": 32, "knowledge_revision": 138, "git_revision": "f9bf1b8704a317ce6d469b8427faa0b8da4b0ed5", "revision_history": [{"85": ""}, {"138": "f9bf1b8704a317ce6d469b8427faa0b8da4b0ed5"}], "hash": "511d0ec7e08bc522ffc754b300f84d59", "format-version": 4, "code-base-name": "schedule_manager_frontend", "filename": "schedule_manager_frontend/tsconfig.json"}